sha256py/__init__.py
sha256py/__main__.py
sha256py/cli.py
sha256py/core.py
sha256py/utils.py
sha256py-0.1.1.dist-info/licenses/LICENSE
sha256py-0.1.1.dist-info/METADATA
sha256py-0.1.1.dist-info/WHEEL
sha256py-0.1.1.dist-info/entry_points.txt
sha256py-0.1.1.dist-info/top_level.txt
sha256py-0.1.1.dist-info/RECORD
