Metadata-Version: 2.4
Name: sha256py
Version: 0.1.1
Summary: Pure Python SHA-256 hashing implementation
Author-email: Lenard Felix <contact@lenardfelix.de>
Requires-Python: >=3.7
License-File: LICENSE
Dynamic: license-file
